{"id":"zettel.20260421162310","title":"AI-native Software Engineering memindahkan gravitasi kerja engineering ke orkestrasi dan verifikasi AI","desc":"Beban utama tidak lagi di penulisan kode manual, melainkan pada niat, konteks, constraint, dan pemeriksaan output AI.","tags":["ai-native","software-engineering","workflow"],"custom":{},"fname":"zettel.20260421162310","type":"note","vault":{"fsPath":"vault"},"contentHash":"0d333b44ed013ce980d827a4a21a231b","updated":1776914280699,"created":1776914280699,"links":[{"type":"frontmatterTag","from":{"fname":"zettel.20260421162310","id":"zettel.20260421162310","vaultName":"vault"},"value":"tags.ai-native","alias":"ai-native","xvault":false,"to":{"fname":"tags.ai-native"}},{"type":"frontmatterTag","from":{"fname":"zettel.20260421162310","id":"zettel.20260421162310","vaultName":"vault"},"value":"tags.software-engineering","alias":"software-engineering","xvault":false,"to":{"fname":"tags.software-engineering"}},{"type":"frontmatterTag","from":{"fname":"zettel.20260421162310","id":"zettel.20260421162310","vaultName":"vault"},"value":"tags.workflow","alias":"workflow","xvault":false,"to":{"fname":"tags.workflow"}},{"type":"wiki","from":{"fname":"zettel.20260421162310","id":"zettel.20260421162310","vaultName":"vault"},"value":"zettel.20260421162253","position":{"start":{"line":53,"column":3,"offset":2001},"end":{"line":53,"column":28,"offset":2026},"indent":[]},"xvault":false,"sameFile":false,"to":{"fname":"zettel.20260421162253"}},{"type":"wiki","from":{"fname":"zettel.20260421162310","id":"zettel.20260421162310","vaultName":"vault"},"value":"zettel.moc.software-architecture","position":{"start":{"line":54,"column":3,"offset":2129},"end":{"line":54,"column":39,"offset":2165},"indent":[]},"xvault":false,"sameFile":false,"to":{"fname":"zettel.moc.software-architecture"}},{"from":{"fname":"zettel","id":"zettel","vaultName":"vault"},"type":"backlink","position":{"start":{"line":112,"column":3,"offset":9978},"end":{"line":112,"column":28,"offset":10003},"indent":[]},"value":"zettel.20260421162310"},{"from":{"fname":"zettel.20260421162320","id":"zettel.20260421162320","vaultName":"vault"},"type":"backlink","position":{"start":{"line":48,"column":3,"offset":1700},"end":{"line":48,"column":28,"offset":1725},"indent":[]},"value":"zettel.20260421162310"},{"from":{"fname":"zettel.20260421192951","id":"zettel.20260421192951","vaultName":"vault"},"type":"backlink","position":{"start":{"line":44,"column":3,"offset":2244},"end":{"line":44,"column":28,"offset":2269},"indent":[]},"value":"zettel.20260421162310"},{"from":{"fname":"zettel.20260421193756","id":"zettel.20260421193756","vaultName":"vault"},"type":"backlink","position":{"start":{"line":67,"column":3,"offset":2911},"end":{"line":67,"column":28,"offset":2936},"indent":[]},"value":"zettel.20260421162310"},{"from":{"fname":"zettel.literature.thoughtworks-ai-native-engineering","id":"zettel.literature.thoughtworks-ai-native-engineering","vaultName":"vault"},"type":"backlink","position":{"start":{"line":29,"column":3,"offset":1421},"end":{"line":29,"column":28,"offset":1446},"indent":[]},"value":"zettel.20260421162310"},{"from":{"fname":"zettel.moc.ai-native","id":"zettel.moc.ai-native","vaultName":"vault"},"type":"backlink","position":{"start":{"line":25,"column":3,"offset":1497},"end":{"line":25,"column":28,"offset":1522},"indent":[]},"value":"zettel.20260421162310"},{"from":{"fname":"zettel.moc.software-architecture","id":"zettel.moc.software-architecture","vaultName":"vault"},"type":"backlink","position":{"start":{"line":40,"column":3,"offset":2404},"end":{"line":40,"column":28,"offset":2429},"indent":[]},"value":"zettel.20260421162310"}],"anchors":{"pertanyaan-yang-dibuka":{"type":"header","text":"Pertanyaan yang dibuka","value":"pertanyaan-yang-dibuka","line":16,"column":0,"depth":2},"klaim-utama":{"type":"header","text":"Klaim utama","value":"klaim-utama","line":22,"column":0,"depth":2},"gravitasi-kerja-di-tiga-mode":{"type":"header","text":"Gravitasi kerja di tiga mode","value":"gravitasi-kerja-di-tiga-mode","line":26,"column":0,"depth":2},"konsekuensi-perubahan-gravitasi":{"type":"header","text":"Konsekuensi perubahan gravitasi","value":"konsekuensi-perubahan-gravitasi","line":32,"column":0,"depth":2},"classic":{"type":"header","text":"Classic","value":"classic","line":34,"column":0,"depth":3},"modern":{"type":"header","text":"Modern","value":"modern","line":40,"column":0,"depth":3},"ai-native":{"type":"header","text":"AI-native","value":"ai-native","line":46,"column":0,"depth":3},"titik-beratnya-berubah":{"type":"header","text":"Titik beratnya berubah","value":"titik-beratnya-berubah","line":52,"column":0,"depth":2},"peringatan":{"type":"header","text":"Peringatan","value":"peringatan","line":59,"column":0,"depth":2},"lihat-juga":{"type":"header","text":"Lihat juga","value":"lihat-juga","line":65,"column":0,"depth":2}},"children":[],"parent":"zettel","data":{}}
